Workbook
Name NativeTimeline_Transaction_Date: #REF!
Name NativeTimeline_Transaction_Date1: #REF!
Name NativeTimeline_Transaction_Date2: #REF!
Name Slicer_Book: #REF!
Name Slicer_Book1: #REF!
Name Slicer_Currency: #REF!
Name Slicer_Currency1: #REF!
Name Slicer_Currency2: #REF!
Name Slicer_Currency3: #REF!
Name Slicer_Products: #REF!
Name Slicer_Products1: #REF!

Sheet Links you need
A2: Excel should come with your PC or buy the license from MS store or get it from a computer operator around you
A4: SQL Server: https://www.youtube.com/watch?v=tV20RClXehQ
A6: Power BI: https://www.microsoft.com/en-us/download/details.aspx?id=58494
A8: Python: https://colab.google/
A10: Learn how to use colab here: https://www.youtube.com/watch?v=FXKMmilL70w&pp=ygUXaG93IHRvIHVzZSBnb29nbGUgY29sYWI%3D
A12: My YouTube is a guide for you: https://www.youtube.com/@EzekielAleke
A14: Connect with me on substack: https://substack.com/@ezekielaleke?

Sheet TEXT FXN
A1: Products | B1: Transaction Date | C1: Currency | D1: Total | F1: CONCATENATE | G1: CONCAT | H1: TEXTJOIN | I1: & | J1: TEXTSPLIT | K1: LEFT | L1: RIGHT | M1: MID | N1: Substitute | O1: LEN | P1: UPPER | Q1: LOWER | R1: PROPER | S1: UNIQUE | T1: TRIM | U1: REPT | V1: EXACT | W1: TRANSPOSE
A2: PYTHON, EXCEL AND SQL CLASS | B2: 45230.688 | C2: GHS | D2: 398
A3: DATA ANALYSIS MADE EASY | B3: 45056.385 | C3: GHS | D3: 156
A4: DATA ANALYSIS MADE EASY | B4: 45060.966 | C4: GHS | D4: 154
A5: DATA ANALYSIS MADE EASY | B5: 45075.895 | C5: GHS | D5: 147
A6: DATA ANALYSIS MADE EASY | B6: 45186.813 | C6: GHS | D6: 99
A7: DATA ANALYSIS MADE EASY | B7: 45107.724 | C7: GHS | D7: 92
A8: DATA ANALYSIS MADE EASY | B8: 45106.536 | C8: GHS | D8: 91
A9: DATA ANALYSIS MADE EASY | B9: 45129.331 | C9: GHS | D9: 91
A10: DATA ANALYSIS MADE EASY | B10: 45135.766 | C10: GHS | D10: 86
A11: DATA ANALYSIS MADE EASY | B11: 45142.959 | C11: GHS | D11: 85
A12: DATA ANALYSIS MADE EASY | B12: 45142.426 | C12: GHS | D12: 85
A13: DATA ANALYSIS MADE EASY | B13: 45160.955 | C13: GHS | D13: 85
... A86: DATA ANALYSIS MADE EASY | B86: 45117.963 | C86: GBP | D86: 8.51

Sheet AGG FXN
A1: Products | B1: Transaction Date | C1: Currency | D1: Revenue
A2: DATA ANALYSIS MADE EASY | B2: 45071 | C2: UGX | D2: 44143
A3: DATA ANALYSIS MADE EASY | B3: 45054 | C3: TZS | D3: 28162
A4: DATA ANALYSIS MADE EASY | B4: 45022 | C4: RWF | D4: 13200.02 | E4: SUM | F4: SUMIF | G4: SUMIFS | H4: AVG | I4: AVGIF | J4: AVGIFS | K4: COUNT | L4: COUNTA | M4: COUNTIF | N4: COUNTIFS | O4: MAX | P4: MAXIFS | Q4: MIN | R4: MINIFS
A5: Techies Guide | B5: 45107 | C5: GHS | D5: 59
A6: DATA ANALYSIS MADE EASY | B6: 45069 | C6: NGN | D6: 10500
A7: DATA ANALYSIS MADE EASY | B7: 45069 | C7: NGN | D7: 10500
A8: DATA ANALYSIS MADE EASY | B8: 45069 | C8: NGN | D8: 10500
A9: DATA ANALYSIS MADE EASY | B9: 45067 | C9: NGN | D9: 10500
A10: DATA ANALYSIS MADE EASY | B10: 45067 | C10: NGN | D10: 10500
A11: DATA ANALYSIS MADE EASY | B11: 45066 | C11: NGN | D11: 10500
A12: DATA ANALYSIS MADE EASY | B12: 45066 | C12: NGN | D12: 10500
A13: DATA ANALYSIS MADE EASY | B13: 45063 | C13: NGN | D13: 10500
A14: DATA ANALYSIS MADE EASY | B14: 45062 | C14: NGN | D14: 10500
A15: DATA ANALYSIS MADE EASY | B15: 45072 | C15: XAF | D15: 7299.03
A16: DATA ANALYSIS MADE EASY | B16: 45061 | C16: XAF | D16: 7171.38
... A424: Techies Guide | B424: 45089 | C424: GBP | D424: 20
D425: =SUBTOTAL(109,'AGG FXN'!$D$2:$D$424) -> 1375020.5

Sheet EXCEL TABLE
A1: Products | B1: Transaction Date | C1: Currency | D1: Revenue
A2: DATA ANALYSIS MADE EASY | B2: 45072 | C2: XAF | D2: 7299.03
A3: DATA ANALYSIS MADE EASY | B3: 45061 | C3: XAF | D3: 7171.38
A4: 12 Strategies | B4: 45029 | C4: USD | D4: 15
A5: 12 Strategies | B5: 45030 | C5: USD | D5: 15
A6: DATA ANALYSIS MADE EASY | B6: 45030 | C6: USD | D6: 15
A7: DATA ANALYSIS MADE EASY | B7: 45071 | C7: UGX | D7: 44143
A8: DATA ANALYSIS MADE EASY | B8: 44998 | C8: UGX | D8: 44000
A9: DATA ANALYSIS MADE EASY | B9: 45054 | C9: TZS | D9: 28162
A10: DATA ANALYSIS MADE EASY | B10: 45022 | C10: RWF | D10: 13200.02
A11: DATA ANALYSIS MADE EASY | B11: 45066 | C11: NGN | D11: 10500
A12: DATA ANALYSIS MADE EASY | B12: 45069 | C12: NGN | D12: 10500
A13: DATA ANALYSIS MADE EASY | B13: 45069 | C13: NGN | D13: 10500
... A25: 12 Strategies | B25: 44998 | C25: NGN | D25: 5500

Sheet POWER QUERY
A1: Yes it is empty

Sheet COND FORMATTING AND DATA
A1: Make | B1: Color | C1: Mileage | D1: Price | E1: Cost | F1: Profit
A2: Chevrolet Impala | B2: White | C2: 140811 | D2: 2340 | E2: 2000 | F2: 1000
A3: Honda Civic | B3: White | C3: 138789 | D3: 2723 | E3: 1900 | F3: 823
A4: Toyota Corolla | B4: Blue | C4: 130684 | D4: 2798 | E4: 2200 | F4: 598
A5: Ford F-150 | B5: Black | C5: 89073 | D5: 3950 | E5: 3000 | F5: 950
A6: Nissan Altima | B6: Green | C6: 69847 | D6: 3826 | E6: 3000 | F6: 826
A7: Ford Mustang | B7: Blue | C7: 41560 | D7: 3706 | E7: 3100 | F7: 606
A8: Honda Accord | B8: Blue | C8: 101354 | D8: 2000 | E8: 1500 | F8: 500
A9: Honda Accord | B9: Blue | C9: 95135 | D9: 2500 | E9: 2000 | F9: 500
A10: Honda Accord | B10: red | C10: 63512 | D10: 4000 | E10: 3000 | F10: 100
A11: Chevrolet Malibu | B11: White | C11: 139300 | D11: 3361 | E11: 3000 | F11: 361
A12: Chevrolet Silverado | B12: Green | C12: 109231 | D12: 4959 | E12: 4500 | F12: 459
A13: Chevrolet Impala | B13: Black | C13: 87675 | D13: 3791 | E13: 3500 | F13: 291
... A19: Ford Escape | B19: Red | C19: 40826 | D19: 4397 | E19: 3900 | F19: 497

Sheet Look UP FXN
A1: Car | B1: Model | C1: Date | D1: Color | E1: Mileage | F1: Price | G1: Cost
A2: Honda | B2: Accord | C2: 45204.9 | D2: Red | E2: 63512 | F2: 4000 | G2: 3000 | J2: VLOOKUP | L2: XLOOKUP
A3: Toyota | B3: Camry | C3: 45202.673 | D3: Black | E3: 75006 | F3: 2198 | G3: 1900 | I3: Price Honda
A4: Nissan | B4: Altima | C4: 45202.502 | D4: Green | E4: 69847 | F4: 3826 | G4: 3000
A5: Ford | B5: F-150 | C5: 45196.467 | D5: Black | E5: 89073 | F5: 3950 | G5: 3000 | I5: Cost Camry
A6: Chevrolet | B6: Silverado | C6: 45194.702 | D6: Green | E6: 109231 | F6: 4959 | G6: 4500 | I6: black car
A7: Dodge | B7: Charger | C7: 45182.672 | D7: Silver | E7: 34853 | F7: 4349 | G7: 3500
J8: HLOOKUP | L8: INDEX/MATCH
A18: {=TRANSPOSE(A1:G7)} -> Car | B18: Honda | C18: Toyota | D18: Nissan | E18: Ford | F18: Chevrolet | G18: Dodge
A19: Model | B19: Accord | C19: Camry | D19: Altima | E19: F-150 | F19: Silverado | G19: Charger
A20: Date | B20: 45204.9 | C20: 45202.673 | D20: 45202.502 | E20: 45196.467 | F20: 45194.702 | G20: 45182.672
A21: Color | B21: Red | C21: Black | D21: Green | E21: Black | F21: Green | G21: Silver
A22: Mileage | B22: 63512 | C22: 75006 | D22: 69847 | E22: 89073 | F22: 109231 | G22: 34853
A23: Price | B23: 4000 | C23: 2198 | D23: 3826 | E23: 3950 | F23: 4959 | G23: 4349
A24: Cost | B24: 3000 | C24: 1900 | D24: 3000 | E24: 3000 | F24: 4500 | G24: 3500

Sheet Sheet1
B1: (ALL)

Sheet CONDITIONAL FXN
K1: Name | L1: Age | M1: Age group | N1: IFS | O1: Switch
A2: Products | B2: Transaction Date | C2: Currency | D2: Revenue | F2: IF | G2: IFS | H2: SWITCH | I2: Nested IF | K2: Vera | L2: 21
A3: DATA ANALYSIS MADE EASY | B3: 45244 | C3: KES | D3: 1042 | K3: Eze | L3: 70
A4: DATA ANALYSIS MADE EASY | B4: 45243 | C4: NGN | D4: 5500 | K4: Joko | L4: 65
A5: DATA ANALYSIS MADE EASY | B5: 45243 | C5: NGN | D5: 5500 | K5: Ridwan | L5: 31
A6: DATA ANALYSIS MADE EASY | B6: 45118 | C6: NGN | D6: 5500 | K6: Leke | L6: 40
A7: DATA ANALYSIS MADE EASY | B7: 45118 | C7: USD | D7: 15 | K7: Oyin | L7: 18
A8: DATA ANALYSIS MADE EASY | B8: 45109 | C8: USD | D8: 15 | K8: Ekpe | L8: 51
A9: DATA ANALYSIS MADE EASY | B9: 45109 | C9: KES | D9: 1058 | K9: Funke | L9: 20
A10: DATA ANALYSIS MADE EASY | B10: 45108 | C10: USD | D10: 15 | K10: Nelson | L10: 75
A11: DATA ANALYSIS MADE EASY | B11: 45108 | C11: NGN | D11: 5500
A12: Techies Guide | B12: 45107 | C12: GHS | D12: 59
A13: DATA ANALYSIS MADE EASY | B13: 45107 | C13: NGN | D13: 5500 | K13: 30 Young
A14: Techies Guide | B14: 45107 | C14: GHS | D14: 59 | K14: 31-50 Adult
A15: DATA ANALYSIS MADE EASY | B15: 45107 | C15: GHS | D15: 92 | K15: 51- Old
A16: DATA ANALYSIS MADE EASY | B16: 45107 | C16: GBP | D16: 8.51
A17: Techies Guide | B17: 45107 | C17: GHS | D17: 59
A18: Techies Guide | B18: 45107 | C18: GHS | D18: 59
A19: Techies Guide | B19: 45107 | C19: GHS | D19: 59
A20: Techies Guide | B20: 45107 | C20: GHS | D20: 59
A21: Techies Guide | B21: 45107 | C21: GHS | D21: 59
A22: Techies Guide | B22: 45107 | C22: GHS | D22: 59
A23: Techies Guide | B23: 45107 | C23: GHS | D23: 59
A24: Techies Guide | B24: 45107 | C24: GHS | D24: 59
A25: DATA ANALYSIS MADE EASY | B25: 45106 | C25: USD | D25: 15
A26: DATA ANALYSIS MADE EASY | B26: 45106 | C26: GHS | D26: 91
A27: DATA ANALYSIS MADE EASY | B27: 45106 | C27: USD | D27: 15
... A92: DATA ANALYSIS MADE EASY | B92: 45081 | C92: GBP | D92: 9.31
A93: Total | D93: =SUBTOTAL(109,'CONDITIONAL FXN'!$D$3:$D$92) -> 198039.05

Sheet Power Pivot

Sheet PT AND PC
A1: Products | B1: Transaction Date | C1: Currency | D1: REVENUE | E1: Total Revenue
A2: DAME | B2: 45118 | C2: NGN | D2: 5500 | E2: {=_xludf.SWITCH('PT AND PC'!$C2,"NGN",'PT AND PC'!$D2,"USD",'PT AND PC'!$D2*1000,"GBP",'PT AND PC'!$D2*1200,"KES",'PT AND PC'!$D2*5.4,"GHS",'PT AND PC'!$D2*80,"XAF",'PT AND PC'!$D2*1.6,"ZAR",'PT AND PC'!$D2*15,"TZS",'PT AND PC'!$D2*0.2,"RWF",'PT AND PC'!$D2*0.4)} -> #NAME?
A3: DAME | B3: 45118 | C3: USD | D3: 15 | E3: {=_xludf.SWITCH('PT AND PC'!$C3,"NGN",'PT AND PC'!$D3,"USD",'PT AND PC'!$D3*1000,"GBP",'PT AND PC'!$D3*1200,"KES",'PT AND PC'!$D3*5.4,"GHS",'PT AND PC'!$D3*80,"XAF",'PT AND PC'!$D3*1.6,"ZAR",'PT AND PC'!$D3*15,"TZS",'PT AND PC'!$D3*0.2,"RWF",'PT AND PC'!$D3*0.4)} -> #NAME?
A4: DAME | B4: 45118 | C4: XAF | D4: 4239.28 | E4: {=_xludf.SWITCH('PT AND PC'!$C4,"NGN",'PT AND PC'!$D4,"USD",'PT AND PC'!$D4*1000,"GBP",'PT AND PC'!$D4*1200,"KES",'PT AND PC'!$D4*5.4,"GHS",'PT AND PC'!$D4*80,"XAF",'PT AND PC'!$D4*1.6,"ZAR",'PT AND PC'!$D4*15,"TZS",'PT AND PC'!$D4*0.2,"RWF",'PT AND PC'!$D4*0.4)} -> #NAME?
A5: Techies Guide | B5: 45107 | C5: GHS | D5: 59 | E5: {=_xludf.SWITCH('PT AND PC'!$C5,"NGN",'PT AND PC'!$D5,"USD",'PT AND PC'!$D5*1000,"GBP",'PT AND PC'!$D5*1200,"KES",'PT AND PC'!$D5*5.4,"GHS",'PT AND PC'!$D5*80,"XAF",'PT AND PC'!$D5*1.6,"ZAR",'PT AND PC'!$D5*15,"TZS",'PT AND PC'!$D5*0.2,"RWF",'PT AND PC'!$D5*0.4)} -> #NAME?
A6: DAME | B6: 45117 | C6: NGN | D6: 5500 | E6: {=_xludf.SWITCH('PT AND PC'!$C6,"NGN",'PT AND PC'!$D6,"USD",'PT AND PC'!$D6*1000,"GBP",'PT AND PC'!$D6*1200,"KES",'PT AND PC'!$D6*5.4,"GHS",'PT AND PC'!$D6*80,"XAF",'PT AND PC'!$D6*1.6,"ZAR",'PT AND PC'!$D6*15,"TZS",'PT AND PC'!$D6*0.2,"RWF",'PT AND PC'!$D6*0.4)} -> #NAME?
A7: DAME | B7: 45117 | C7: NGN | D7: 5500 | E7: {=_xludf.SWITCH('PT AND PC'!$C7,"NGN",'PT AND PC'!$D7,"USD",'PT AND PC'!$D7*1000,"GBP",'PT AND PC'!$D7*1200,"KES",'PT AND PC'!$D7*5.4,"GHS",'PT AND PC'!$D7*80,"XAF",'PT AND PC'!$D7*1.6,"ZAR",'PT AND PC'!$D7*15,"TZS",'PT AND PC'!$D7*0.2,"RWF",'PT AND PC'!$D7*0.4)} -> #NAME?
A8: DAME | B8: 45116 | C8: NGN | D8: 5500 | E8: {=_xludf.SWITCH('PT AND PC'!$C8,"NGN",'PT AND PC'!$D8,"USD",'PT AND PC'!$D8*1000,"GBP",'PT AND PC'!$D8*1200,"KES",'PT AND PC'!$D8*5.4,"GHS",'PT AND PC'!$D8*80,"XAF",'PT AND PC'!$D8*1.6,"ZAR",'PT AND PC'!$D8*15,"TZS",'PT AND PC'!$D8*0.2,"RWF",'PT AND PC'!$D8*0.4)} -> #NAME?
A9: DAME | B9: 45114 | C9: NGN | D9: 5500 | E9: {=_xludf.SWITCH('PT AND PC'!$C9,"NGN",'PT AND PC'!$D9,"USD",'PT AND PC'!$D9*1000,"GBP",'PT AND PC'!$D9*1200,"KES",'PT AND PC'!$D9*5.4,"GHS",'PT AND PC'!$D9*80,"XAF",'PT AND PC'!$D9*1.6,"ZAR",'PT AND PC'!$D9*15,"TZS",'PT AND PC'!$D9*0.2,"RWF",'PT AND PC'!$D9*0.4)} -> #NAME?
A10: DAME | B10: 45112 | C10: NGN | D10: 5500 | E10: {=_xludf.SWITCH('PT AND PC'!$C10,"NGN",'PT AND PC'!$D10,"USD",'PT AND PC'!$D10*1000,"GBP",'PT AND PC'!$D10*1200,"KES",'PT AND PC'!$D10*5.4,"GHS",'PT AND PC'!$D10*80,"XAF",'PT AND PC'!$D10*1.6,"ZAR",'PT AND PC'!$D10*15,"TZS",'PT AND PC'!$D10*0.2,"RWF",'PT AND PC'!$D10*0.4)} -> #NAME?
A11: DAME | B11: 45112 | C11: NGN | D11: 5500 | E11: {=_xludf.SWITCH('PT AND PC'!$C11,"NGN",'PT AND PC'!$D11,"USD",'PT AND PC'!$D11*1000,"GBP",'PT AND PC'!$D11*1200,"KES",'PT AND PC'!$D11*5.4,"GHS",'PT AND PC'!$D11*80,"XAF",'PT AND PC'!$D11*1.6,"ZAR",'PT AND PC'!$D11*15,"TZS",'PT AND PC'!$D11*0.2,"RWF",'PT AND PC'!$D11*0.4)} -> #NAME?
A12: DAME | B12: 45110 | C12: NGN | D12: 5500 | E12: {=_xludf.SWITCH('PT AND PC'!$C12,"NGN",'PT AND PC'!$D12,"USD",'PT AND PC'!$D12*1000,"GBP",'PT AND PC'!$D12*1200,"KES",'PT AND PC'!$D12*5.4,"GHS",'PT AND PC'!$D12*80,"XAF",'PT AND PC'!$D12*1.6,"ZAR",'PT AND PC'!$D12*15,"TZS",'PT AND PC'!$D12*0.2,"RWF",'PT AND PC'!$D12*0.4)} -> #NAME?
A13: DAME | B13: 45109 | C13: USD | D13: 15 | E13: {=_xludf.SWITCH('PT AND PC'!$C13,"NGN",'PT AND PC'!$D13,"USD",'PT AND PC'!$D13*1000,"GBP",'PT AND PC'!$D13*1200,"KES",'PT AND PC'!$D13*5.4,"GHS",'PT AND PC'!$D13*80,"XAF",'PT AND PC'!$D13*1.6,"ZAR",'PT AND PC'!$D13*15,"TZS",'PT AND PC'!$D13*0.2,"RWF",'PT AND PC'!$D13*0.4)} -> #NAME?
... A425: Techies Guide | B425: 45089 | C425: GBP | D425: 20 | E425: {=_xludf.SWITCH('PT AND PC'!$C425,"NGN",'PT AND PC'!$D425,"USD",'PT AND PC'!$D425*1000,"GBP",'PT AND PC'!$D425*1200,"KES",'PT AND PC'!$D425*5.4,"GHS",'PT AND PC'!$D425*80,"XAF",'PT AND PC'!$D425*1.6,"ZAR",'PT AND PC'!$D425*15,"TZS",'PT AND PC'!$D425*0.2,"RWF",'PT AND PC'!$D425*0.4)} -> #NAME?

Sheet Project
